bmiselect/__init__.py
bmiselect/main.py
bmiselect/models/ARD.py
bmiselect/models/Bayesian_MI_LASSO.py
bmiselect/models/Horseshoe.py
bmiselect/models/Laplace.py
bmiselect/models/Ridge.py
bmiselect/models/Spike_laplace.py
bmiselect/models/Spike_ridge.py
bmiselect/models/__init__.py
bmiselect/utils/__init__.py
bmiselect/utils/evaluation.py
bmiselect/utils/genDS_MAR.py
bmiselect/utils/genDS_MCAR.py
bmiselect-0.0.9.dist-info/LICENSE
bmiselect-0.0.9.dist-info/METADATA
bmiselect-0.0.9.dist-info/WHEEL
bmiselect-0.0.9.dist-info/top_level.txt
bmiselect-0.0.9.dist-info/RECORD
