Metadata-Version: 2.1
Name: bmiselect
Version: 0.0.9
Summary: Bayesian MI-LASSO for variable selection on multiply-imputed data. 
Home-page: https://github.com/zjg540066169/Bmiselect
Author: Jungang Zou
Author-email: jungang.zou@gmail.com
Project-URL: Code, https://github.com/zjg540066169/Bmiselect
Classifier: Development Status :: 2 - Pre-Alpha
Classifier: Intended Audience :: Science/Research
Classifier: License :: OSI Approved :: Apache Software License
Classifier: Natural Language :: English
Classifier: Programming Language :: Python
Classifier: Programming Language :: Python :: 3 :: Only
Classifier: Programming Language :: Python :: 3.7
Classifier: Programming Language :: Python :: 3.8
Classifier: Programming Language :: Python :: 3.9
Classifier: Topic :: Scientific/Engineering :: Information Analysis
Requires-Python: >=3.7.*
License-File: LICENSE
Requires-Dist: pymc3 (>=3.11.5)
Requires-Dist: theano-pymc (>=1.1.2)
Requires-Dist: mkl (>=2.4.0)
Requires-Dist: mkl-service (>=2.4.0)
Requires-Dist: numpy
Requires-Dist: matplotlib
Requires-Dist: scikit-learn
Requires-Dist: pandas
Requires-Dist: seaborn
Requires-Dist: arviz
Requires-Dist: xarray
Requires-Dist: statsmodels
